LICENSE.txt
MANIFEST.in
README.md
README.rst
blog-post.md
blog-post.rst
setup.cfg
setup.py
tastic/__init__.py
tastic/__version__.py
tastic/cl_utils.py
tastic/default_settings.yaml
tastic/reminders.py
tastic/tastic.py
tastic/utKit.py
tastic.egg-info/PKG-INFO
tastic.egg-info/SOURCES.txt
tastic.egg-info/dependency_links.txt
tastic.egg-info/entry_points.txt
tastic.egg-info/not-zip-safe
tastic.egg-info/requires.txt
tastic.egg-info/top_level.txt
tastic/commonutils/__init__.py
tastic/commonutils/getpackagepath.py
tastic/tests/__init__.py
tastic/tests/test_reminders.py
tastic/tests/test_tastic.py
tastic/tests/test_tutorial.py
tastic/tests/input/example_settings.yaml
tastic/tests/input/saturday-tasks.taskpaper
tastic/tests/input/ssdr3.taskpaper
tastic/tests/input/tasks_imported_from_reminders.taskpaper
tastic/tests/input/tastic.yaml
tastic/tests/input/home/lists/single-tasks.taskpaper
tastic/tests/input/home/lists/watch-list.taskpaper
tastic/tests/input/home/templates/new-coding-project.taskpaper
tastic/tests/input/home/templates/tax-returns.taskpaper
tastic/tests/input/work/checklists/daily-review.taskpaper
tastic/tests/input/work/checklists/monthly-review.taskpaper
tastic/tests/input/work/checklists/pack-for-holiday.taskpaper
tastic/tests/input/work/lists/single-tasks.taskpaper
tastic/tests/input/work/lists/watch-list.taskpaper
tastic/tests/output/example_settings.yaml
tastic/tests/output/nosetest_debug.log
tastic/tests/output/saturday-tasks.taskpaper
tastic/tests/output/ssdr3.taskpaper
tastic/tests/output/tasks_imported_from_reminders.taskpaper
tastic/tests/output/tastic.yaml
tastic/tests/output/home/lists/single-tasks.taskpaper
tastic/tests/output/home/lists/watch-list.taskpaper
tastic/tests/output/home/templates/new-coding-project.taskpaper
tastic/tests/output/home/templates/tax-returns.taskpaper
tastic/tests/output/work/checklists/daily-review.taskpaper
tastic/tests/output/work/checklists/monthly-review.taskpaper
tastic/tests/output/work/checklists/pack-for-holiday.taskpaper
tastic/tests/output/work/lists/single-tasks.taskpaper
tastic/tests/output/work/lists/watch-list.taskpaper
tastic/workspace/__init__.py
tastic/workspace/sync.py
tastic/workspace/workspace.py
