Metadata-Version: 1.1
Name: tastic
Version: 1.8.2
Summary: A python package for working with taskpaper documents
Home-page: https://github.com/thespacedoctor/tastic
Author: David Young
Author-email: davidrobertyoung@gmail.com
License: MIT
Download-URL: https://github.com/thespacedoctor/tastic/archive/v1.8.2.zip
Keywords: taskpaper
Platform: UNKNOWN
Classifier: Development Status :: 4 - Beta
Classifier: License :: OSI Approved :: MIT License
Classifier: Programming Language :: Python :: 2.7
Classifier: Topic :: Utilities
